deepclassifer/__init__.py
deepclassifer/__version__.py
deepclassifer/layers/__init__.py
deepclassifer/layers/lstm.py
deepclassifer/models/__init__.py
deepclassifer/models/basemodel.py
deepclassifer/models/bertdpcnn.py
deepclassifer/models/berthan.py
deepclassifer/models/bertrcnn.py
deepclassifer/models/berttextcnn.py
deepclassifer/models/dpcnn.py
deepclassifer/models/han.py
deepclassifer/models/rcnn.py
deepclassifer/models/textcnn.py
deepclassifer/trainers/__init__.py
deepclassifer/trainers/trainer.py
deepclassifier/__init__.py
deepclassifier/layers/__init__.py
deepclassifier/layers/lstm.py
deepclassifier/models/__init__.py
deepclassifier/models/basemodel.py
deepclassifier/models/bertdpcnn.py
deepclassifier/models/berthan.py
deepclassifier/models/bertrcnn.py
deepclassifier/models/berttextcnn.py
deepclassifier/models/dpcnn.py
deepclassifier/models/han.py
deepclassifier/models/rcnn.py
deepclassifier/models/textcnn.py
deepclassifier/trainers/__init__.py
deepclassifier/trainers/trainer.py
examples/__init__.py
examples/example_berttextcnn.py
examples/example_textcnn.py
examples/preprocessing.py
deepclassifier-0.0.6.dist-info/LICENSE
deepclassifier-0.0.6.dist-info/METADATA
deepclassifier-0.0.6.dist-info/WHEEL
deepclassifier-0.0.6.dist-info/top_level.txt
deepclassifier-0.0.6.dist-info/RECORD
